{
  "effects": [
    {
      "id": "male-heavy-breathing",
      "type": "loop",
      "src": [
        "/book_data/audios/sound/male-heavy-breathing.mp3"
      ],
      "playOnLoad": true
    },
    {
      "id": "notification-to-be-continued",
      "type": "oneShot",
      "src": [
        "/book_data/audios/sound/achievement-unlocked.mp3"
      ],
      "notification": {
        "id": "notification-to-be-continued",
        "text": "Продолжение следует..",
        "className": "info"
      },
      "playOnLoad": true
    }
  ],
  "pageInfo": {
    "num": 14
  }
}